xiuxian_back/__init__.py
xiuxian_back/back_util.py
xiuxian_back/backconfig.py
xiuxian_back-0.30.dist-info/METADATA
xiuxian_back-0.30.dist-info/WHEEL
xiuxian_back-0.30.dist-info/top_level.txt
xiuxian_back-0.30.dist-info/RECORD
